EduSim/__init__.py
EduSim/Agent/__init__.py
EduSim/Agent/agent.py
EduSim/Agent/base.py
EduSim/Agent/utils.py
EduSim/Envs/Env.py
EduSim/Envs/KS.py
EduSim/Envs/Learner.py
EduSim/Envs/QBamk.py
EduSim/Envs/Reward.py
EduSim/Envs/Tester.py
EduSim/Envs/__init__.py
EduSim/Envs/base.py
EduSim/Envs/KSS/Env.py
EduSim/Envs/KSS/KS.py
EduSim/Envs/KSS/Learner.py
EduSim/Envs/KSS/QBank.py
EduSim/Envs/KSS/Tester.py
EduSim/Envs/KSS/__init__.py
EduSim/utils/__init__.py
EduSim/utils/irt.py
EduSim-0.0.2.dist-info/DESCRIPTION.rst
EduSim-0.0.2.dist-info/METADATA
EduSim-0.0.2.dist-info/RECORD
EduSim-0.0.2.dist-info/WHEEL
EduSim-0.0.2.dist-info/metadata.json
EduSim-0.0.2.dist-info/top_level.txt
tests/__init__.py
tests/conftest.py
tests/test_env.py
tests/test_learner.py
tests/test_reward.py
tests/test_KSS/__init__.py
tests/test_KSS/conftest.py
tests/test_KSS/test_KSS.py
tests/test_KSS/test_learner.py
tests/test_KSS/test_q_bank.py
tests/test_KSS/test_tester.py
tests/test_agent/__init__.py
tests/test_agent/conftest.py
tests/test_agent/test_agent.py
tests/test_agent/test_utils.py
